SheriAPI/__init__.py
SheriAPI/api.py
SheriAPI/endpoints.py
SheriAPI/enums.py
SheriAPI/errors.py
SheriAPI-1.0.4.dist-info/LICENSE
SheriAPI-1.0.4.dist-info/METADATA
SheriAPI-1.0.4.dist-info/WHEEL
SheriAPI-1.0.4.dist-info/top_level.txt
SheriAPI-1.0.4.dist-info/RECORD
