Metadata-Version: 2.1
Name: SheriAPI
Version: 1.0.4
Summary: A simple API wrapper to interact with the Sheri Blossom API.
Home-page: https://github.com/Nanofaux/SheriAPI
Author: Nanofaux
Author-email: nanofaux@hotmail.com
License: MIT
Keywords: furry,SheriAPI,sheri blossom,yiff,fur,discord
Classifier: Development Status :: 5 - Production/Stable
Classifier: License :: OSI Approved :: MIT License
Classifier: Intended Audience :: Developers
Classifier: Operating System :: OS Independent
Classifier: Programming Language :: Python :: 3
Requires-Python: >=3.6
License-File: LICENSE
Requires-Dist: aiohttp ~=3.7.3
Requires-Dist: async-timeout ~=3.0.1
Requires-Dist: attrs ~=20.3.0
Requires-Dist: certifi ~=2020.12.5
Requires-Dist: chardet ~=3.0.4
Requires-Dist: idna ~=3.1
Requires-Dist: multidict ~=5.1.0
Requires-Dist: Pygments ~=2.7.4
Requires-Dist: python-dotenv ~=0.15.0
Requires-Dist: typing-extensions ~=3.7.4.3
Requires-Dist: wincertstore ~=0.2
Requires-Dist: yarl ~=1.6.3
